topsis/__init__.py
topsis/__main__.py
topsis_khushi_102103479-1.0.0.dist-info/LICENSE
topsis_khushi_102103479-1.0.0.dist-info/METADATA
topsis_khushi_102103479-1.0.0.dist-info/WHEEL
topsis_khushi_102103479-1.0.0.dist-info/entry_points.txt
topsis_khushi_102103479-1.0.0.dist-info/top_level.txt
topsis_khushi_102103479-1.0.0.dist-info/RECORD
