Metadata-Version: 2.1
Name: topsis-khushi-102103479
Version: 1.0.0
Summary: Performs TOPSIS dor multi-criteria decision making
Home-page: https://github.com/khushi-attri/topsis
Author: Khushi Atti
Author-email: kattri_be21@thapar.edu
License: MIT
Classifier: License :: OSI Approved :: MIT License
Classifier: Programming Language :: Python :: 3.8
Classifier: Programming Language :: Python :: 3.9
Classifier: Programming Language :: Python :: 3.10
License-File: LICENSE
